{"assets":{"B7857E94474B218E63A9C6E38D710664":{"type":"texture","index":0,"assetRequest":{"type":"slide","state":"contents","slide":"none"},"url":{"native":"assets\/BAE07E06-7B13-45AA-BE2F-032DFAC77943.pdf"},"width":1920,"height":1080},"6E23322451119D0D6B9E379743D4C68C":{"type":"texture","index":1,"assetRequest":{"type":"slide","state":"contents","slide":"none"},"url":{"native":"assets\/BAE07E06-7B13-45AA-BE2F-032DFAC77943.pdf"},"width":1920,"height":1080}},"events":[{"effects":[{"beginTime":0,"baseLayer":{"animations":[],"initialState":{"affineTransform":[1,0,0,1,0,0],"masksToBounds":false,"rotation":0,"scale":1,"position":{"pointX":960,"pointY":540},"width":1920,"sublayerTransform":[1,0,0,0,0,1,0,0,0,0,1,0,0,0,0,1],"contentsRect":{"y":0,"x":0,"width":1,"height":1},"opacity":1,"edgeAntialiasingMask":251658240,"height":1080,"hidden":false,"anchorPoint":{"pointX":0.5,"pointY":0.5}},"objectID":"0","layers":[{"animations":[],"initialState":{"affineTransform":[1,0,0,1,0,0],"masksToBounds":false,"rotation":0,"scale":1,"position":{"pointX":960,"pointY":540},"width":1920,"sublayerTransform":[1,0,0,0,0,1,0,0,0,0,1,-0.00035007912466775983,0,0,0,1],"contentsRect":{"y":0,"x":0,"width":1,"height":1},"opacity":1,"edgeAntialiasingMask":251658240,"height":1080,"hidden":false,"anchorPoint":{"pointX":0.5,"pointY":0.5}},"layers":[{"animations":[],"layers":[],"texturedRectangle":{"isBackgroundTexture":false,"singleTextureOpacity":1,"textureType":0,"textBaseline":0,"textXHeight":0,"isVerticalText":false},"initialState":{"affineTransform":[1,0,0,1,0,0],"masksToBounds":false,"rotation":0,"scale":1,"position":{"pointX":960,"pointY":540},"width":1920,"sublayerTransform":[1,0,0,0,0,1,0,0,0,0,1,0,0,0,0,1],"contentsRect":{"y":0,"x":0,"width":1,"height":1},"opacity":1,"edgeAntialiasingMask":0,"height":1080,"hidden":false,"anchorPoint":{"pointX":0.5,"pointY":0.5}},"texture":"6E23322451119D0D6B9E379743D4C68C"},{"animations":[{"additive":false,"timeOffset":0,"beginTime":0,"from":{"scalar":false},"repeatCount":0,"fillMode":"both","duration":0.01,"autoreverses":false,"property":"hidden","to":{"scalar":true},"removedOnCompletion":false}],"layers":[],"texturedRectangle":{"isBackgroundTexture":false,"singleTextureOpacity":1,"textureType":0,"textBaseline":0,"textXHeight":0,"isVerticalText":false},"initialState":{"affineTransform":[1,0,0,1,0,0],"masksToBounds":false,"rotation":0,"scale":1,"position":{"pointX":960,"pointY":540},"width":1920,"sublayerTransform":[1,0,0,0,0,1,0,0,0,0,1,0,0,0,0,1],"contentsRect":{"y":0,"x":0,"width":1,"height":1},"opacity":1,"edgeAntialiasingMask":0,"height":1080,"hidden":false,"anchorPoint":{"pointX":0.5,"pointY":0.5}},"texture":"B7857E94474B218E63A9C6E38D710664"}]}]},"effects":[],"duration":0.01,"type":"transition","attributes":{"direction":0},"name":"none","objectID":"0"}],"automaticPlay":false,"hyperlinks":[],"accessibility":[{"text":"PAGE","targetRectangle":{"y":48.833331763744354,"x":1090.774658203125,"width":27.842031955718994,"height":10}},{"text":"PROJECT","targetRectangle":{"y":48.833331763744354,"x":278.01593017578125,"width":47.86515748500824,"height":10}},{"text":"AR Burnie Activation - Character Render","targetRectangle":{"y":681.99981689453125,"x":1086.9072265625,"width":657.94300000000021,"height":117}},{"text":"pasted-image.pdf","targetRectangle":{"y":50.086681365966797,"x":1846.2767333984375,"width":25.717266082763672,"height":25.717266082763672}},{"text":"ROUND","targetRectangle":{"y":48.833331763744354,"x":967.70794677734375,"width":36.532032132148743,"height":10}},{"text":"THREE","targetRectangle":{"y":61.833336472511292,"x":967.70794677734375,"width":47.616000089406953,"height":15}},{"text":"CLIENT","targetRectangle":{"y":48.833331763744354,"x":49.38671875,"width":37.526719808578491,"height":10}},{"text":"att_hz_lg_lkp_rgb_rev.png","targetRectangle":{"y":63.733304977416992,"x":1065.71484375,"width":242.625,"height":79.28125}},{"text":"pasted-image.tiff","targetRectangle":{"y":0.046875,"x":-1.542572021484375,"width":1039.84375,"height":1079.90625}},{"text":"AT&T EAST","targetRectangle":{"y":344.33413696289062,"x":1086.5333251953125,"width":623.6800012874603,"height":131}},{"text":"plaza at","targetRectangle":{"y":475.33413696289062,"x":1086.5333251953125,"width":561.44000114440905,"height":131}},{"text":"fTx arena","targetRectangle":{"y":606.33413696289062,"x":1086.5333251953125,"width":659.20000128746028,"height":131}},{"text":"DATE","targetRectangle":{"y":49.833331763744354,"x":738.548583984375,"width":26.947500705718994,"height":10}},{"text":"JULY 28, 2021","targetRectangle":{"y":62.833336472511292,"x":737.548583984375,"width":99.240000232458101,"height":15}},{"text":"AT&T","targetRectangle":{"y":61.833336472511292,"x":48.38671875,"width":35.71200007152558,"height":15}},{"text":"EAST PLAZA AT FTX ARENA","targetRectangle":{"y":61.833336472511292,"x":277.01593017578125,"width":203.12400041127194,"height":15}},{"text":"Round Two","targetRectangle":{"y":950.97259521484375,"x":1090.50634765625,"width":90.738000072419709,"height":26}},{"text":"October 18, 2021","targetRectangle":{"y":976.97259521484375,"x":1090.50634765625,"width":131.04000012874599,"height":26}},{"text":"Wasserman","targetRectangle":{"y":1002.9725952148438,"x":1090.50634765625,"width":93.870000072419543,"height":26}}],"baseLayer":{"animations":[],"initialState":{"affineTransform":[1,0,0,1,0,0],"masksToBounds":false,"rotation":0,"scale":1,"position":{"pointX":960,"pointY":540},"width":1920,"sublayerTransform":[1,0,0,0,0,1,0,0,0,0,1,0,0,0,0,1],"contentsRect":{"y":0,"x":0,"width":1,"height":1},"opacity":1,"edgeAntialiasingMask":251658240,"height":1080,"hidden":false,"anchorPoint":{"pointX":0.5,"pointY":0.5}},"objectID":"0","layers":[{"animations":[],"initialState":{"affineTransform":[1,0,0,1,0,0],"masksToBounds":false,"rotation":0,"scale":1,"position":{"pointX":960,"pointY":540},"width":1920,"sublayerTransform":[1,0,0,0,0,1,0,0,0,0,1,-0.00035007912466775983,0,0,0,1],"contentsRect":{"y":0,"x":0,"width":1,"height":1},"opacity":1,"edgeAntialiasingMask":251658240,"height":1080,"hidden":false,"anchorPoint":{"pointX":0.5,"pointY":0.5}},"layers":[{"animations":[],"layers":[],"texturedRectangle":{"isBackgroundTexture":false,"singleTextureOpacity":1,"textureType":0,"textBaseline":0,"textXHeight":0,"isVerticalText":false},"initialState":{"affineTransform":[1,0,0,1,0,0],"masksToBounds":false,"rotation":0,"scale":1,"position":{"pointX":960,"pointY":540},"width":1920,"sublayerTransform":[1,0,0,0,0,1,0,0,0,0,1,0,0,0,0,1],"contentsRect":{"y":0,"x":0,"width":1,"height":1},"opacity":1,"edgeAntialiasingMask":0,"height":1080,"hidden":false,"anchorPoint":{"pointX":0.5,"pointY":0.5}},"texture":"B7857E94474B218E63A9C6E38D710664"}]}]}}]}